moptipyapps/__init__.py
moptipyapps/py.typed
moptipyapps/version.py
moptipyapps/binpacking2d/__init__.py
moptipyapps/binpacking2d/bks.bib
moptipyapps/binpacking2d/bks.py
moptipyapps/binpacking2d/experiment.py
moptipyapps/binpacking2d/instance.py
moptipyapps/binpacking2d/instances.txt
moptipyapps/binpacking2d/make_instances.py
moptipyapps/binpacking2d/packing.py
moptipyapps/binpacking2d/packing_result.py
moptipyapps/binpacking2d/packing_space.py
moptipyapps/binpacking2d/packing_statistics.py
moptipyapps/binpacking2d/plot_packing.py
moptipyapps/binpacking2d/encodings/__init__.py
moptipyapps/binpacking2d/encodings/ibl_encoding_1.py
moptipyapps/binpacking2d/encodings/ibl_encoding_2.py
moptipyapps/binpacking2d/instgen/__init__.py
moptipyapps/binpacking2d/instgen/errors.py
moptipyapps/binpacking2d/instgen/errors_and_hardness.py
moptipyapps/binpacking2d/instgen/experiment.py
moptipyapps/binpacking2d/instgen/hardness.py
moptipyapps/binpacking2d/instgen/inst_decoding.py
moptipyapps/binpacking2d/instgen/instance_space.py
moptipyapps/binpacking2d/instgen/problem.py
moptipyapps/binpacking2d/objectives/__init__.py
moptipyapps/binpacking2d/objectives/bin_count.py
moptipyapps/binpacking2d/objectives/bin_count_and_empty.py
moptipyapps/binpacking2d/objectives/bin_count_and_last_empty.py
moptipyapps/binpacking2d/objectives/bin_count_and_last_skyline.py
moptipyapps/binpacking2d/objectives/bin_count_and_last_small.py
moptipyapps/binpacking2d/objectives/bin_count_and_lowest_skyline.py
moptipyapps/binpacking2d/objectives/bin_count_and_small.py
moptipyapps/order1d/__init__.py
moptipyapps/order1d/distances.py
moptipyapps/order1d/instance.py
moptipyapps/order1d/space.py
moptipyapps/prodsched/__init__.py
moptipyapps/prodsched/instance.py
moptipyapps/prodsched/instances.py
moptipyapps/prodsched/mfc_generator.py
moptipyapps/prodsched/multistatistics.py
moptipyapps/prodsched/rop_experiment.py
moptipyapps/prodsched/rop_multisimulation.py
moptipyapps/prodsched/rop_simulation.py
moptipyapps-0.8.81.dist-info/licenses/LICENSE
moptipyapps-0.8.81.dist-info/METADATA
moptipyapps-0.8.81.dist-info/WHEEL
moptipyapps-0.8.81.dist-info/top_level.txt
moptipyapps-0.8.81.dist-info/RECORD
