Metadata-Version: 2.4
Name: moptipyapps
Version: 0.8.81
Summary: Applications of Metaheuristic Optimization in Python.
Home-page: https://thomasweise.github.io/moptipyapps
Author: Thomas Weise
Author-email: tweise@ustc.edu.cn
Maintainer: Thomas Weise
Maintainer-email: tweise@ustc.edu.cn
License: GPL 3.0
Project-URL: Documentation, https://thomasweise.github.io/moptipyapps
Project-URL: Source, https://github.com/thomasWeise/moptipyapps/
Project-URL: Tracker, https://github.com/thomasWeise/moptipyapps/issues
Keywords: bin packing
Classifier: Development Status :: 4 - Beta
Classifier: Framework :: Matplotlib
Classifier: Intended Audience :: Developers
Classifier: Intended Audience :: Education
Classifier: Intended Audience :: Science/Research
Classifier: Natural Language :: English
Classifier: Natural Language :: German
Classifier: Natural Language :: Chinese (Simplified)
Classifier: Operating System :: Microsoft :: Windows
Classifier: Operating System :: POSIX :: Linux
Classifier: Programming Language :: Python :: 3 :: Only
Classifier: Programming Language :: Python :: 3.12
Classifier: Topic :: Education
Classifier: Topic :: Scientific/Engineering :: Artificial Intelligence
Classifier: Topic :: Scientific/Engineering :: Mathematics
Classifier: Topic :: Scientific/Engineering :: Visualization
Requires-Python: >=3.12
License-File: LICENSE
Requires-Dist: certifi>=2025.11.12
Requires-Dist: defusedxml>=0.7.1
Requires-Dist: moptipy>=0.9.164
Requires-Dist: numba>=0.63.0
Requires-Dist: numpy>=2.3.5
Requires-Dist: matplotlib>=3.10.7
Requires-Dist: pycommons>=0.8.81
Requires-Dist: urllib3>=2.6.1
Dynamic: description
Dynamic: description-content-type
Dynamic: license-file
